neon_display/__init__.py
neon_display/__main__.py
neon_display/services/__init__.py
neon_display/services/opencv_backend/__init__.py
neon_display-0.0.2a1.dist-info/LICENSE.md
neon_display-0.0.2a1.dist-info/METADATA
neon_display-0.0.2a1.dist-info/WHEEL
neon_display-0.0.2a1.dist-info/entry_points.txt
neon_display-0.0.2a1.dist-info/top_level.txt
neon_display-0.0.2a1.dist-info/RECORD
