Metadata-Version: 2.1
Name: neon-display
Version: 0.0.2a1
Summary: Neon Display Module
Home-page: https://github.com/NeonGeckoCom/neon_display
Author: Neongecko
Author-email: developers@neon.ai
License: BSD-3-Clause
Platform: UNKNOWN
Requires-Dist: mycroft-messagebus-client (!=0.9.2,!=0.9.3,~=0.9)
Requires-Dist: neon-utils (~=0.13)
Requires-Dist: ovos-core[bus] (~=0.0.1)
Requires-Dist: numpy
Requires-Dist: imutils
Requires-Dist: opencv-python
Requires-Dist: opencv-contrib-python
